{
  "@id": "TradeInProductType",
  "name": "Trade In Product Type",
  "@type": "Class",
  "description": "Defines a list of product types that are allowed as trade-in tender.",
  "subjectArea": "PaymentMethod",
  "entityGroup": "PaymentMethod",
  "properties": [
    {
      "@id": "id",
      "@type": "Property"
    }
  ],
  "schema": {
    "@id": "b0a30ee1-c1be-4212-b4b4-f1c204c90b70",
    "@type": "Shape",
    "targetClass": "TradeInProductType",
    "properties": [
      {
        "path": "systemModstamp",
        "@id": "9da4b917-feb8-4494-b575-fa388d82653a",
        "datatype": "xsd:time",
        "maxCount": "1",
        "minCount": "1"
      },
      {
        "path": "lastModifiedDate",
        "@id": "bee7ca3b-e834-44b4-bf7f-f722bf3feed7",
        "datatype": "xsd:time",
        "maxCount": "1",
        "minCount": "1"
      },
      {
        "path": "implementorType",
        "@id": "87ab6abb-09d1-4e2e-b1b1-7a4613a7f03c",
        "datatype": "xsd:string",
        "maxCount": "1",
        "minCount": "1"
      },
      {
        "path": "id",
        "@id": "d26aa17d-3275-4131-9111-5dc2bbfda95f",
        "datatype": "cim:id",
        "maxCount": "1",
        "minCount": "1"
      },
      {
        "path": "externalSourceId",
        "@id": "0173f5a8-3d38-4040-8545-e21ca0f1aac1",
        "datatype": "xsd:string",
        "maxCount": "1"
      },
      {
        "path": "externalRecordId",
        "@id": "4032ac90-9b41-47e7-a7a7-56067a85d2fd",
        "datatype": "xsd:string",
        "maxCount": "1"
      },
      {
        "path": "createdDate",
        "@id": "1751a165-55b0-4e3e-9f9f-26ed58ca9484",
        "datatype": "xsd:time",
        "maxCount": "1",
        "minCount": "1"
      }
    ]
  }
}